modelangelo/__init__.py
modelangelo/bibtex.py
modelangelo/constants.py
modelangelo/logo.jpeg
modelangelo/protocols.conf
modelangelo/protocols/__init__.py
modelangelo/protocols/protocol_model_angelo.py
modelangelo/tests/__init__.py
modelangelo/tests/tests_model_angelo.py
modelangelo/viewers/__init__.py
modelangelo/viewers/viewer.py
scipion_em_modelangelo-3.1.1.dist-info/LICENSE
scipion_em_modelangelo-3.1.1.dist-info/METADATA
scipion_em_modelangelo-3.1.1.dist-info/WHEEL
scipion_em_modelangelo-3.1.1.dist-info/entry_points.txt
scipion_em_modelangelo-3.1.1.dist-info/top_level.txt
scipion_em_modelangelo-3.1.1.dist-info/RECORD
