Metadata-Version: 2.1
Name: scipion-em-modelangelo
Version: 3.1.1
Summary: Scipion plugin for modelangelo.
Home-page: https://github.com/scipion-em/scipion-em-modelangelo
Author: Pablo Conesa
Author-email: scipion@cnb.cnb.csic.es
License: UNKNOWN
Project-URL: Bug Reports, https://github.com/scipion-em/scipion-em-modelangelo/issues
Project-URL: Source, https://github.com/scipion-em/scipion-em-modelangelo/
Keywords: scipion cryoem imageprocessing modelling modelangelo scipion-3.0
Platform: UNKNOWN
Classifier: Development Status :: 4 - Beta
Classifier: License :: OSI Approved :: GNU General Public License v3 (GPLv3)
Classifier: Programming Language :: Python :: 3
Requires-Dist: scipion-pyworkflow
Requires-Dist: scipion-em
